Metadata-Version: 2.1
Name: dswmagic
Version: 3.0
Summary: dsw ipython magic command
Home-page: UNKNOWN
Author: xibai
License: UNKNOWN
Platform: UNKNOWN
Classifier: Programming Language :: Python :: 3.5
